mintlify_changelog/__init__.py
mintlify_changelog/analyzer.py
mintlify_changelog/cli.py
mintlify_changelog/config.py
mintlify_changelog/core.py
mintlify_changelog/formatters.py
mintlify_changelog/prompts.py
mintlify_changelog-1.0.3.dist-info/licenses/LICENSE
mintlify_changelog-1.0.3.dist-info/METADATA
mintlify_changelog-1.0.3.dist-info/WHEEL
mintlify_changelog-1.0.3.dist-info/entry_points.txt
mintlify_changelog-1.0.3.dist-info/top_level.txt
mintlify_changelog-1.0.3.dist-info/RECORD
